PythonDbs/__init__.py
PythonDbs-0.0.10.dist-info/METADATA
PythonDbs-0.0.10.dist-info/WHEEL
PythonDbs-0.0.10.dist-info/top_level.txt
PythonDbs-0.0.10.dist-info/RECORD
