Metadata-Version: 2.1
Name: PythonDbs
Version: 0.0.10
Summary: sqlite3 extension
Author: Jordan
Author-email: <jordybhunter10@outlook.com>
Keywords: python,first package
Classifier: Development Status :: 3 - Alpha
Classifier: Intended Audience :: Other Audience
Classifier: Programming Language :: Python :: 3
Classifier: Operating System :: Microsoft :: Windows
